pyprembly/__init__.py
pyprembly/base.py
pyprembly/business.py
pyprembly/configuration.py
pyprembly/document.py
pyprembly/exceptions.py
pyprembly/face.py
pyprembly/radar.py
pyprembly/utils.py
pyprembly/data/__init__.py
pyprembly/data/ghana.py
pyprembly/data/kenya.py
pyprembly/data/nigeria.py
pyprembly/data/rwanda.py
pyprembly/data/sierra_leone.py
pyprembly/data/south_africa.py
pyprembly/data/uganda.py
test/__init__.py
test/integration/__init__.py
test/integration/test_face_recognition.py
test/integration/test_ghana.py
test/integration/test_global_business.py
test/integration/test_kenya.py
test/integration/test_nigeria.py
test/integration/test_sierra_leone.py
test/integration/test_south_africa.py
test/integration/test_uganda.py
pyprembly-0.0.4.dist-info/LICENSE
pyprembly-0.0.4.dist-info/METADATA
pyprembly-0.0.4.dist-info/WHEEL
pyprembly-0.0.4.dist-info/top_level.txt
pyprembly-0.0.4.dist-info/RECORD
