Metadata-Version: 2.1
Name: pyprembly
Version: 0.0.4
Summary: Python bindings for the Prembly IdentityPass API
Home-page: https://github.com/olakayCoder1/pyprembly
Author: Olanrewaju Kabiru
Author-email: programmerolakay@gmail.com
License: MIT
Keywords: api,client,prembly
Platform: UNKNOWN
Classifier: Development Status :: 4 - Beta
Classifier: Programming Language :: Python
Classifier: Programming Language :: Python :: 3
Classifier: Programming Language :: Python :: 3.6
Classifier: Programming Language :: Python :: 3.7
Classifier: Topic :: Software Development :: Libraries :: Python Modules
Classifier: Environment :: Web Environment
Classifier: Intended Audience :: Developers
Classifier: License :: OSI Approved :: MIT License
Requires-Python: >=3.x
License-File: LICENSE
Requires-Dist: requests
Requires-Dist: python-dotenv
Requires-Dist: urllib3
